MANIFEST.in
README.md
requirements.txt
setup.py
pyrasta/__init__.py
pyrasta/base.py
pyrasta/crs.py
pyrasta/exceptions.py
pyrasta/raster.py
pyrasta/utils.py
pyrasta.egg-info/PKG-INFO
pyrasta.egg-info/SOURCES.txt
pyrasta.egg-info/dependency_links.txt
pyrasta.egg-info/not-zip-safe
pyrasta.egg-info/requires.txt
pyrasta.egg-info/top_level.txt
pyrasta/io_/__init__.py
pyrasta/io_/files.py
pyrasta/tools/__init__.py
pyrasta/tools/calculator.py
pyrasta/tools/clip.py
pyrasta/tools/conversion.py
pyrasta/tools/dem.py
pyrasta/tools/filters.py
pyrasta/tools/mapping.py
pyrasta/tools/mask.py
pyrasta/tools/merge.py
pyrasta/tools/polygonize.py
pyrasta/tools/rasterize.py
pyrasta/tools/srtm.py
pyrasta/tools/stats.py
pyrasta/tools/windows.py