Metadata-Version: 2.1
Name: pyrasta
Version: 1.3.24
Summary: Some tools for fast and easy raster processing
Home-page: https://framagit.org/benjaminpillot/pyrasta
Author: Benjamin Pillot
Author-email: benjaminpillot@riseup.net
License: MIT
Platform: UNKNOWN
Requires-Python: >=3
